mcp_staten/__init__.py
mcp_staten/main.py
mcp_staten-0.1.2.dist-info/licenses/LICENSE
mcp_staten-0.1.2.dist-info/METADATA
mcp_staten-0.1.2.dist-info/WHEEL
mcp_staten-0.1.2.dist-info/entry_points.txt
mcp_staten-0.1.2.dist-info/top_level.txt
mcp_staten-0.1.2.dist-info/RECORD
